MANIFEST.in
README.md
setup.cfg
setup.py
pyada/CMakeLists.txt
pyada/__ad.cpp
pyada/__ad.pyx
pyada/__init__.pxd
pyada/__init__.py
pyada/__loda.cpp
pyada/__loda.pyx
pyada/ad.pxd
pyada.egg-info/PKG-INFO
pyada.egg-info/SOURCES.txt
pyada.egg-info/dependency_links.txt
pyada.egg-info/not-zip-safe
pyada.egg-info/requires.txt
pyada.egg-info/top_level.txt
pyada/__pycache__/__init__.cpython-36.pyc
pyada/__pycache__/__init__.cpython-37.pyc
pyada/__pycache__/common.cpython-36.pyc
pyada/src/CMakeLists.txt
pyada/src/bagged_forest.cpp
pyada/src/bagged_forest.hpp
pyada/src/command_parser.cpp
pyada/src/command_parser.hpp
pyada/src/conv_forest.cpp
pyada/src/conv_forest.hpp
pyada/src/facade_forest.cpp
pyada/src/facade_forest.hpp
pyada/src/feature_contribution.hpp
pyada/src/forest.cpp
pyada/src/forest.hpp
pyada/src/globals.hpp
pyada/src/isolation_forest.cpp
pyada/src/isolation_forest.hpp
pyada/src/log_writer.cpp
pyada/src/log_writer.hpp
pyada/src/main.cpp
pyada/src/main.hpp
pyada/src/metric.cpp
pyada/src/metric.hpp
pyada/src/r_forest.cpp
pyada/src/r_forest.hpp
pyada/src/tree.cpp
pyada/src/tree.hpp
pyada/src/utility.cpp
pyada/src/utility.hpp
pyada/src/.idea/.name
pyada/src/.idea/encodings.xml
pyada/src/.idea/misc.xml
pyada/src/.idea/modules.xml
pyada/src/.idea/src.iml
pyada/src/.idea/vcs.xml
pyada/src/.idea/workspace.xml
pyada/src/.idea/codeStyles/codeStyleConfig.xml
pyada/src/cmake-build-debug/CMakeCache.txt
pyada/src/cmake-build-debug/Makefile
pyada/src/cmake-build-debug/cmake_install.cmake
pyada/src/cmake-build-debug/libiforestlib.a
pyada/src/cmake-build-debug/pyiforest.cbp
pyada/src/cmake-build-debug/CMakeFiles/CMakeDirectoryInformation.cmake
pyada/src/cmake-build-debug/CMakeFiles/CMakeOutput.log
pyada/src/cmake-build-debug/CMakeFiles/Makefile.cmake
pyada/src/cmake-build-debug/CMakeFiles/Makefile2
pyada/src/cmake-build-debug/CMakeFiles/TargetDirectories.txt
pyada/src/cmake-build-debug/CMakeFiles/clion-environment.txt
pyada/src/cmake-build-debug/CMakeFiles/clion-log.txt
pyada/src/cmake-build-debug/CMakeFiles/cmake.check_cache
pyada/src/cmake-build-debug/CMakeFiles/feature_tests.bin
pyada/src/cmake-build-debug/CMakeFiles/feature_tests.c
